{
  "word": "willow",
  "ipa": {
    "us": "ˈwɪləʊ",
    "uk": "ˈwɪloʊ"
  },
  "sentences": [
    {
      "en": "A pair of orioles alighted on the frisking branch of a weeping willow.",
      "cn": "一对黄鹂飞落在拂动着的柳树枝条上."
    },
    {
      "en": "He has also captured pollen from alder, pine and willow.",
      "cn": "他还从桤树、松树和柳树上捕捉到了花粉。"
    },
    {
      "en": "He worships that big willow south of the house.",
      "cn": "他很崇拜房子南面的那颗大柳树。"
    },
    {
      "en": "Huei - fang was leaning against a willow, dabbing her eyes with a handkerchief.",
      "cn": "四小姐蕙芳正靠在一棵杨柳树上用手帕揉眼睛."
    },
    {
      "en": "I don't think I can stand much of Lock Willow.",
      "cn": "我实在无法在洛克威洛住下去."
    },
    {
      "en": "Jenny weaves baskets from willow she grows herself.",
      "cn": "珍妮用她自己种的柳树的枝条编篮子。"
    },
    {
      "en": "She walked slowly, head lowered, a willow branch in her hand.",
      "cn": "她低着头慢慢地走着, 手里拿了一枝柳条."
    },
    {
      "en": "The baskets are woven from strips of willow.",
      "cn": "这些篮子是用柳条编的。"
    },
    {
      "en": "The river Till strained among some score of willow - covered, marshy islets.",
      "cn": "铁尔河蜿蜒在几十个长满了柳树的沼泽小岛之间."
    },
    {
      "en": "The river was sparsely lined with willow trees.",
      "cn": "河边疏疏落落有几棵柳树."
    },
    {
      "en": "The willow trees cast their shadows all around.",
      "cn": "柳荫匝地."
    },
    {
      "en": "The willow's shadow falls on the lake.",
      "cn": "垂柳的影子倒映在湖面上."
    },
    {
      "en": "These willow saplings will put out fresh leaves very soon.",
      "cn": "这些柳树苗不久就要长出新叶了."
    },
    {
      "en": "Willow branches swept the river's surface.",
      "cn": "柳枝拂掠着河面."
    },
    {
      "en": "Willow catkins are fluttering in the air.",
      "cn": "柳絮在空中飞舞."
    },
    {
      "en": "Willow trees breaking out into buds foretell the coming of spring.",
      "cn": "柳枝绽青报春来."
    },
    {
      "en": "Willow twigs are pliable.",
      "cn": "柳条很软."
    }
  ],
  "rel_words": [],
  "synos": [
    {
      "pos": "n",
      "words": [
        {
          "words": [
            "Salix"
          ],
          "tran_cn": "[林]柳树；[木]柳木制品"
        }
      ]
    }
  ],
  "phrases": [
    {
      "phrase": "weeping willow",
      "tran_cn": "[植]垂柳；[俚]枕头"
    },
    {
      "phrase": "willow tree",
      "tran_cn": "柳树"
    }
  ],
  "trans": [
    {
      "pos": "adj",
      "tran_cn": "柳木制的"
    },
    {
      "pos": "n",
      "tran_cn": "柳树，柳木制品",
      "tran_en": "a type of tree that has long thin branches and grows near water, or the wood from this tree"
    }
  ],
  "exchange": {
    "pl": [
      "willows"
    ]
  }
}