{
  "word": "horned",
  "ipa": {
    "us": "hɔ:nd",
    "uk": "hɔrnd"
  },
  "sentences": [
    {
      "en": "a horned toad",
      "cn": "角蟾"
    },
    {
      "en": "About more than 100 people were horned in the bullfighting this year.",
      "cn": "在今年的斗牛中,约有一百多人被牛抵伤."
    },
    {
      "en": "APG brake system was horned China Famous Brand Products in China.",
      "cn": "亚太股份的汽车制动系统为中国名牌产品."
    },
    {
      "en": "English breed of short - horned cattle.",
      "cn": "英国品种的短角肉用牛."
    },
    {
      "en": "He horned in with some suggestions while we were talking.",
      "cn": "我们正在讨论时,他打断我们的话提出一些建议."
    },
    {
      "en": "horned cattle",
      "cn": "有角的牛"
    },
    {
      "en": "Horned Overseers can commit a suicide explosion.",
      "cn": "角魔督军可以自爆."
    },
    {
      "en": "I see the outline of the horned Man - in - Black.",
      "cn": "黑色长角的轮廓映入我的眼中."
    },
    {
      "en": "Its horned armrests and legs were covered with goat's fur.",
      "cn": "这张椅子的扶手和凳脚长角,并披着羊皮."
    },
    {
      "en": "Lindamy write anything on a piece horned it to the woman.",
      "cn": "汤米在一张纸上写了什么然后递给了这个女孩子."
    },
    {
      "en": "The horned god take me through infernal journeys.",
      "cn": "黑暗魔王带我走过地狱的旅程."
    },
    {
      "en": "The oldest known horned dinosaur in North America is called Zuniceratops.",
      "cn": "目前在北美地区发现的最为古老的有角恐龙是祖尼角龙."
    },
    {
      "en": "The reference is to the horned head of an animal.",
      "cn": "参考是对动物的有角的头."
    },
    {
      "en": "The rhino horned the explorer.",
      "cn": "这头犀牛用牛角顶撞这位探险者."
    },
    {
      "en": "The young bull horned the old cow out of the herd.",
      "cn": "小公牛用角把老母牛从牛群中顶了出去."
    },
    {
      "en": "This is a horned cattle.",
      "cn": "这是一只有角的牛。"
    },
    {
      "en": "When the wheel has turned to Yule light the log the Horned One rules.",
      "cn": "当轮子转到圣诞节上,发光的日志制定着有角的一位."
    }
  ],
  "rel_words": [
    {
      "pos": "adj",
      "words": [
        {
          "word": "hornless",
          "tran_cn": " 无角的"
        },
        {
          "word": "horny",
          "tran_cn": " 角的；角状的；淫荡的"
        }
      ]
    },
    {
      "pos": "n",
      "words": [
        {
          "word": "horn",
          "tran_cn": " 喇叭，号角；角"
        },
        {
          "word": "horniness",
          "tran_cn": " 角质；硬质"
        }
      ]
    },
    {
      "pos": "vt",
      "words": [
        {
          "word": "horn",
          "tran_cn": " 装角于"
        }
      ]
    }
  ],
  "synos": [
    {
      "pos": "adj",
      "words": [
        {
          "words": [
            "angular",
            "cornuted"
          ],
          "tran_cn": "有角的；角状的"
        }
      ]
    }
  ],
  "phrases": [
    {
      "phrase": "air horn",
      "tran_cn": "气笛；扬声器"
    },
    {
      "phrase": "anterior horn",
      "tran_cn": "n. [医]前角；[医]腹角"
    },
    {
      "phrase": "cape horn",
      "tran_cn": "合恩角"
    },
    {
      "phrase": "dorsal horn",
      "tran_cn": "背角；[医]灰质后角"
    },
    {
      "phrase": "english horn",
      "tran_cn": "英国管，中音双簧管"
    },
    {
      "phrase": "french horn",
      "tran_cn": "n. 法国号"
    },
    {
      "phrase": "horn antenna",
      "tran_cn": "号角天线"
    },
    {
      "phrase": "horn in",
      "tran_cn": "闯入；侵入"
    },
    {
      "phrase": "hunting horn",
      "tran_cn": "猎号，猎角"
    },
    {
      "phrase": "lift up the horn",
      "tran_cn": "◎显示斗志，不示弱，不屈服"
    },
    {
      "phrase": "posterior horn",
      "tran_cn": "后角；灰质后角"
    },
    {
      "phrase": "rhinoceros horn",
      "tran_cn": "犀牛角"
    }
  ],
  "trans": [
    {
      "pos": "adj",
      "tran_cn": "有角的，角状的",
      "tran_en": "having horns or something that looks like horns"
    },
    {
      "pos": "v",
      "tran_cn": "截短…的角（horn的过去式和过去分词）"
    }
  ],
  "exchange": {}
}