{
  "word": "orgasm",
  "ipa": {
    "us": "ˈɔ:gæzəm",
    "uk": "ˈɔrgæzəm"
  },
  "sentences": [
    {
      "en": "It's not day a girl gets pleasure out of a fake orgasm.",
      "cn": "一次,一女孩获得一家伙而极度兴奋,一考虑家伙极度兴奋污秽的诡计愉快的在外."
    },
    {
      "en": "Obviously, the man's orgasm is very important for human reproduction.",
      "cn": "显然, 男性的性器官在人类生殖中是非常重要的."
    },
    {
      "en": "We shall abolish the orgasm.",
      "cn": "我们要消灭掉性的快感."
    },
    {
      "en": "women who have never had an orgasm",
      "cn": "从未有过性高潮的女性"
    }
  ],
  "rel_words": [],
  "synos": [
    {
      "pos": "n",
      "words": [
        {
          "words": [
            "big O",
            "fever pitch"
          ],
          "tran_cn": "[生理]性高潮；极度兴奋"
        }
      ]
    }
  ],
  "phrases": [],
  "trans": [
    {
      "pos": "n",
      "tran_cn": "极端的兴奋，[医]情欲亢进，性高潮",
      "tran_en": "the greatest point of sexual pleasure"
    }
  ],
  "exchange": {
    "pl": [
      "orgasms"
    ]
  }
}