{
  "word": "tortoise",
  "ipa": {
    "us": "ˈtɔːtəs",
    "uk": "ˈtɔːrtəs"
  },
  "sentences": [
    {
      "en": "A tortoise has a shell on his back.",
      "cn": "乌龟背上有硬壳."
    },
    {
      "en": "Either way, both the hare and tortoise get what they deserve based on how they behave.",
      "cn": "无论如何，野兔和乌龟得到什么都是基于它们的行为举止的。"
    },
    {
      "en": "He had slept, and the tortoise had won the race.",
      "cn": "乌龟跑到了终点, 而他却在那里睡大觉."
    },
    {
      "en": "I saw a big sea tortoise .",
      "cn": "我看见过一个大海龟。"
    },
    {
      "en": "Julia scowled at her jewelled tortoise.",
      "cn": "这时朱莉娅怒视着那只嵌着钻石的乌龟."
    },
    {
      "en": "Run like a tortoise.",
      "cn": "像乌龟一样慢慢跑。"
    },
    {
      "en": "The elephant dwarfed the tortoise.",
      "cn": "那只乌龟跟那头象相比就显得很小."
    },
    {
      "en": "The hare and the tortoise are going to have a race!",
      "cn": "野兔和乌龟要赛跑."
    },
    {
      "en": "The tortoise crept along at a very slow speed.",
      "cn": "乌龟以极慢的速度向前爬."
    },
    {
      "en": "The tortoise crept along at an agonizingly slow speed.",
      "cn": "乌龟以极其缓慢的速度爬行着."
    },
    {
      "en": "The tortoise is so slow, let me have a rest!",
      "cn": "乌龟太慢了, 让我休息一会儿吧!"
    },
    {
      "en": "The tortoise pulled its head into his carapace.",
      "cn": "乌龟把头缩进它的壳里。"
    },
    {
      "en": "The tortoise spends the winter months in hibernation.",
      "cn": "乌龟在冬眠中度过寒冬季节."
    },
    {
      "en": "The tortoise wine the race while the hare is sleeping.",
      "cn": "兔子打盹时,乌龟得胜归."
    },
    {
      "en": "The tortoise wins the race while the hare is sleeping.",
      "cn": "兔子正睡觉时,乌龟赢得了比赛."
    },
    {
      "en": "Tortoise and Snake Hills face each other across the river.",
      "cn": "龟蛇二山隔江相望."
    },
    {
      "en": "Tortoise fuling lotion and ice spring soya - bean milk Wuzhou famous food.",
      "cn": "龟苓膏和冰泉豆浆都是梧州有名的食品."
    },
    {
      "en": "Who runs fast, the hare or the tortoise?",
      "cn": "野兔和乌龟谁跑得快?"
    }
  ],
  "rel_words": [],
  "synos": [
    {
      "pos": "n",
      "words": [
        {
          "words": [
            "turtle",
            "chelonian"
          ],
          "tran_cn": "[脊椎]龟，乌龟（等于testudo）；迟缓的人"
        }
      ]
    }
  ],
  "phrases": [
    {
      "phrase": "tortoise shell",
      "tran_cn": "龟甲；一种类似龟甲的蝴蝶"
    }
  ],
  "trans": [
    {
      "pos": "n",
      "tran_cn": "乌龟，行动迟缓的人（或物）",
      "tran_en": "a slow-moving land animal that can pull its head and legs into the hard round shell that covers its body"
    }
  ],
  "exchange": {
    "pl": [
      "tortoises"
    ]
  }
}