{
  "word": "statesmanlike",
  "ipa": {
    "us": "ˈsteɪtsmənlaɪk",
    "uk": "ˈsteɪtsmənlaɪk"
  },
  "sentences": [
    {
      "en": "He is trying to project a more dignified, statesmanlike image in this election year.",
      "cn": "他正试图在这个选举年中树立一种更加威严、更有政治家风范的形象。"
    },
    {
      "en": "He was widely respected as a wise and statesmanlike governor.",
      "cn": "他作为一位睿智、具备政治家才干的州长而广受尊崇。"
    },
    {
      "en": "his statesmanlike handling of the crisis",
      "cn": "他处理这场危机时表现出的政治家才干"
    },
    {
      "en": "Used when a politician needs to appear statesmanlike and non - partisan.",
      "cn": "政治家想要显得特别重要、特别有风度的时候酷爱此词."
    }
  ],
  "rel_words": [
    {
      "pos": "adj",
      "words": [
        {
          "word": "statesmanly",
          "tran_cn": "与政治家身份相称的；像政治家的"
        }
      ]
    },
    {
      "pos": "n",
      "words": [
        {
          "word": "statesman",
          "tran_cn": "政治家；国务活动家"
        },
        {
          "word": "statesmanship",
          "tran_cn": "政治才能；政治家的风度"
        },
        {
          "word": "stateswoman",
          "tran_cn": "女政治家；有治国才能的女子"
        }
      ]
    }
  ],
  "synos": [],
  "phrases": [],
  "trans": [
    {
      "pos": "adj",
      "tran_cn": "有政治家风格的，有政治家之身份的",
      "tran_en": "showing the qualities of a statesman – used to show approval"
    }
  ],
  "exchange": {}
}