{
  "word": "incest",
  "ipa": {
    "us": "ˈɪnsest",
    "uk": "ˈɪnˌsɛst"
  },
  "sentences": [
    {
      "en": "Abortions would only be allowed in cases of rape or incest.",
      "cn": "只有被强奸或乱伦受孕才允许堕胎。"
    },
    {
      "en": "Our findings dovetailed with a 1978 EEG study of adults who were victims of incest.",
      "cn": "我们的发现与1978年的一项研究,若合符节."
    },
    {
      "en": "The same is true of the conception of incest.",
      "cn": "血亲婚配的观念,也是如此."
    }
  ],
  "rel_words": [
    {
      "pos": "adj",
      "words": [
        {
          "word": "incestuous",
          "tran_cn": " 乱伦的；血亲相奸的；犯乱伦罪的"
        }
      ]
    }
  ],
  "synos": [
    {
      "pos": "n",
      "words": [
        {
          "words": [
            "fornication"
          ],
          "tran_cn": "乱伦；近亲通婚"
        }
      ]
    }
  ],
  "phrases": [],
  "trans": [
    {
      "pos": "n",
      "tran_cn": "乱伦，近亲通婚，乱伦罪，血族相婚",
      "tran_en": "sex between people who are closely related in a family"
    }
  ],
  "exchange": {}
}