{
  "word": "naive",
  "ipa": {
    "us": "naɪˈiːv",
    "uk": "naɪˈiːv"
  },
  "sentences": [
    {
      "en": "a naive young girl",
      "cn": "天真的小女孩"
    },
    {
      "en": "He is so naive as to believe such a lie.",
      "cn": "他竟然幼稚得连这种谎言都相信."
    },
    {
      "en": "He was touchingly naive about sex.",
      "cn": "他对性幼稚得可怜。"
    },
    {
      "en": "Her colourful oils and works on paper have a naive, dreamlike quality.",
      "cn": "她那些色彩斑斓的油画与纸上作品给人一种天真、梦幻般的感觉。"
    },
    {
      "en": "Her paintings have a naive, dreamlike quality.",
      "cn": "她的画作带有质朴、空灵的韵味。"
    },
    {
      "en": "Hsin - mei felt the question was naive beyond a doubt.",
      "cn": "辛楣 觉得这问题无可猜的幼稚."
    },
    {
      "en": "I know I was a naive fool to trust him but he is a real charmer who totally took me in.",
      "cn": "我知道我当初幼稚无知，竟然信任他，可是他真是迷人，把我完全给骗了。"
    },
    {
      "en": "I must have been naive to think we would get my parents' blessing.",
      "cn": "我一定太天真了，竟认为我们会得到我父母的祝福。"
    },
    {
      "en": "It's naive of you to believe he'll do what he says.",
      "cn": "相信他会言行一致,你未免太单纯了."
    },
    {
      "en": "Jim can be so naive sometimes.",
      "cn": "吉姆有时候非常幼稚。"
    },
    {
      "en": "Modern readers would find such naive solution totally unacceptable.",
      "cn": "现代读者会觉得这种天真的结局完全无法接受."
    },
    {
      "en": "She is so naive that she believes everything he tells her.",
      "cn": "她如此天真以致相信他告诉她的一切."
    },
    {
      "en": "She's so naive that she believes everything he tells her.",
      "cn": "她涉世不深以致相信他所告诉她的每一件事."
    },
    {
      "en": "The display of prehistoric monsters is comically naive.",
      "cn": "史前怪物的展览幼稚可笑。"
    },
    {
      "en": "The drama takes an idealistic, even a naive view of the subject.",
      "cn": "这部戏在对待这一主题上有些理想化，甚至是天真。"
    },
    {
      "en": "Their view was that he had been politically naive.",
      "cn": "他们认为他在政治上一直很幼稚。"
    },
    {
      "en": "to be politically naive",
      "cn": "对政治一无所知"
    }
  ],
  "rel_words": [
    {
      "pos": "adv",
      "words": [
        {
          "word": "naively",
          "tran_cn": " 无邪地；天真烂漫地"
        }
      ]
    }
  ],
  "synos": [
    {
      "pos": "adj",
      "words": [
        {
          "words": [
            "behind",
            "ears",
            "green",
            "immature",
            "inexperienced",
            "raw",
            "the",
            "uneducated",
            "uninitiate",
            "uninitiated",
            "unripe",
            "unschooled",
            "unseasoned",
            "unsophisticated",
            "unwise",
            "unworldly",
            "wet"
          ],
          "tran_cn": "不成熟,无经验,不明智"
        },
        {
          "words": [
            "aboveboard",
            "candid",
            "downright",
            "explicit",
            "forthright",
            "foursquare",
            "frank",
            "genuine",
            "guileless",
            "ingenuous",
            "open",
            "open-hearted",
            "outright",
            "sincere",
            "straightforward",
            "undissembling",
            "unequivocal",
            "unfeigned"
          ],
          "tran_cn": "外向,坦诚,直率"
        },
        {
          "words": [
            "artless",
            "childlike",
            "confiding",
            "credulous",
            "dupable",
            "green",
            "gullible",
            "innocent",
            "simple",
            "simple-hearted",
            "trusting",
            "unsuspecting"
          ],
          "tran_cn": "简单,单纯,天真;纯洁,不世故,轻信"
        }
      ]
    },
    {
      "pos": "other",
      "words": [
        {
          "words": [
            "childish"
          ],
          "tran_cn": "其他释义"
        }
      ]
    }
  ],
  "phrases": [],
  "trans": [
    {
      "pos": "adj",
      "tran_cn": "幼稚的，天真的，单纯的",
      "tran_en": "not having much experience of how complicated life is, so that you trust people too much and believe that good things will always happen"
    }
  ],
  "exchange": {
    "er": [
      "naiver"
    ],
    "est": [
      "naivest"
    ],
    "adv": [
      "naively"
    ],
    "noun": [
      "naivety"
    ]
  }
}