{
  "word": "contemplation",
  "ipa": {
    "us": "ˌkɒntəmˈpleɪʃn",
    "uk": "ˌkɑntəmˈpleɪʃn"
  },
  "sentences": [
    {
      "en": "Contemplation was abandoned for action.",
      "cn": "停止思考,起而行动."
    },
    {
      "en": "Each morning the priest spent an hour in quiet contemplation.",
      "cn": "每天早晨牧师都要默祷一小时."
    },
    {
      "en": "He reached his decision after a good deal of contemplation.",
      "cn": "他经过周密思考后作出了决定."
    },
    {
      "en": "He roused himself from his lazy contemplation of the scene beneath him.",
      "cn": "他不再懒洋洋地注视着下面的景色。"
    },
    {
      "en": "He sat there deep in contemplation.",
      "cn": "他坐在那里沉思着。"
    },
    {
      "en": "He spent many hours in deep contemplation.",
      "cn": "他花了多个小时专心思考."
    },
    {
      "en": "He was lost in the contemplation of the landscape.",
      "cn": "他对着眼前的景色沉思起来。"
    },
    {
      "en": "His mind kept branching off into the contemplation of silly things.",
      "cn": "他总不能专心于正题而尽想着愚蠢的事情."
    },
    {
      "en": "I am quite content with philosophic contemplation.",
      "cn": "我非常满足于哲理性的冥想."
    },
    {
      "en": "It is a place of quiet contemplation.",
      "cn": "这是个静心冥想的好地方。"
    },
    {
      "en": "She bought three dresses in contemplation of her trip.",
      "cn": "她为了作一次旅行买了三套衣服."
    },
    {
      "en": "She was lost in contemplation of the scene in front of her.",
      "cn": "她给眼前的这一幕深深地吸引住了."
    },
    {
      "en": "Sophia was charmed with the contemplation of so heroic an action.",
      "cn": "想到这样一种悲壮的行为,苏菲亚不胜陶醉了."
    },
    {
      "en": "The greatest of all pleasures consists in the contemplation of truth.",
      "cn": "所有快乐中最伟大的快乐存在于对真理的沉思之中."
    },
    {
      "en": "The monks spend an hour in contemplation each morning.",
      "cn": "那些修道士每天早上默想一小时。"
    },
    {
      "en": "There is rest and healing in the contemplation of antiquities.",
      "cn": "欣赏古物有休息和疗养之功."
    }
  ],
  "rel_words": [
    {
      "pos": "adj",
      "words": [
        {
          "word": "contemplative",
          "tran_cn": " 沉思的；冥想的；默想的"
        }
      ]
    },
    {
      "pos": "vi",
      "words": [
        {
          "word": "contemplate",
          "tran_cn": " 冥思苦想；深思熟虑"
        }
      ]
    },
    {
      "pos": "vt",
      "words": [
        {
          "word": "contemplate",
          "tran_cn": " 沉思；注视；思忖；预期"
        }
      ]
    }
  ],
  "synos": [
    {
      "pos": "n",
      "words": [
        {
          "words": [
            "reflection",
            "intention",
            "meaning",
            "will",
            "offer"
          ],
          "tran_cn": "沉思；注视；意图"
        }
      ]
    },
    {
      "pos": "other",
      "words": [
        {
          "words": [
            "consideration",
            "deliberation",
            "expectation",
            "intention",
            "prospect",
            "speculation",
            "study",
            "thinking",
            "will"
          ],
          "tran_cn": ""
        }
      ]
    }
  ],
  "phrases": [],
  "trans": [
    {
      "pos": "n",
      "tran_cn": "深思，沉思，凝视",
      "tran_en": "quiet serious thinking about something"
    }
  ],
  "exchange": {}
}