{
  "word": "confirmed",
  "ipa": {
    "us": "kənˈfɜ:md",
    "uk": "kənˈfɜrmd"
  },
  "sentences": [
    {
      "en": "A positive pregnancy test soon confirmed her intuitive feelings.",
      "cn": "阳性孕检结果很快证实了她的直觉。"
    },
    {
      "en": "He confirmed what had long been feared.",
      "cn": "他证实了人们长期以来的担心。"
    },
    {
      "en": "He was confirmed as a member of the Church of England.",
      "cn": "他领受了坚振礼，成为英国国教会的一员。"
    },
    {
      "en": "He was gratified to hear that his idea had been confirmed.",
      "cn": "听到自己的想法得到了认可，他感到很开心。"
    },
    {
      "en": "I'm a confirmed bachelor.",
      "cn": "我抱定了独身的想法。"
    },
    {
      "en": "It has confirmed me in my decision not to become a nun.",
      "cn": "这使我更加坚定了不做修女的决心。"
    },
    {
      "en": "Leonard, a confirmed atheist, simply could not understand.",
      "cn": "伦纳德这位坚定的无神论者实在是无法理解。"
    },
    {
      "en": "Rumours of job losses were later confirmed.",
      "cn": "裁员的传言后来得到了证实。"
    },
    {
      "en": "Subsequent events confirmed our doubts.",
      "cn": "后来发生的事证实了我们的怀疑。"
    },
    {
      "en": "Temperature records have unequivocally confirmed the existence of global warming.",
      "cn": "气温记录清楚无疑地证实了全球气候正在变暖。"
    },
    {
      "en": "The results confirmed his hypothesis on the use of modal verbs.",
      "cn": "结果证实了他的关于情态动词用法的假设."
    },
    {
      "en": "The study confirmed many reports that doctors were improperly trained.",
      "cn": "该调查证实了许多关于医生未接受充分培训的报道。"
    },
    {
      "en": "Then one day his worst fears were confirmed.",
      "cn": "后来有一天，他最担心的事终于发生了。"
    },
    {
      "en": "They confirmed by wireless that she was picking up survivors.",
      "cn": "他们通过无线电证实她在营救幸存者。"
    },
    {
      "en": "Williams has confirmed his position as the world's number one snooker player.",
      "cn": "威廉姆斯巩固了自己世界头号斯诺克选手的地位。"
    }
  ],
  "rel_words": [
    {
      "pos": "adj",
      "words": [
        {
          "word": "confirmable",
          "tran_cn": " 可证实的；可确定的"
        }
      ]
    },
    {
      "pos": "n",
      "words": [
        {
          "word": "confirmation",
          "tran_cn": " 确认；证实；证明；批准"
        }
      ]
    },
    {
      "pos": "vt",
      "words": [
        {
          "word": "confirm",
          "tran_cn": " 确认；确定；证实；批准；使巩固"
        }
      ]
    }
  ],
  "synos": [
    {
      "pos": "adj",
      "words": [
        {
          "words": [
            "accepted",
            "accredited",
            "acknowledged",
            "approved",
            "authorized",
            "endorsed",
            "licensed",
            "official",
            "ratified",
            "recognized",
            "sanctioned",
            "warranted"
          ],
          "tran_cn": "批准了的,认可了的,有效的"
        },
        {
          "words": [
            "accurate",
            "attested",
            "authenticated",
            "certified",
            "correct",
            "corroborated",
            "demonstrated",
            "documented",
            "factual",
            "notarized",
            "proven",
            "right",
            "substantiated",
            "to",
            "true",
            "valid",
            "validated",
            "verified"
          ],
          "tran_cn": "真实的,确实的"
        },
        {
          "words": [
            "authentic",
            "bona",
            "chronic",
            "complete",
            "deep-rooted",
            "deep-seated",
            "dyed-in-the-wool",
            "established",
            "fide",
            "fixed",
            "genuine",
            "habitual",
            "ingrained",
            "inveterate",
            "real",
            "rooted",
            "through-and-through"
          ],
          "tran_cn": "真正的,根深蒂固的,慢性的"
        },
        {
          "words": [
            "absolute",
            "certain",
            "clinched",
            "conclusive",
            "decided",
            "decisive",
            "definite",
            "final",
            "firm",
            "positive",
            "sealed",
            "settled",
            "sure"
          ],
          "tran_cn": "确定了的,决定了的"
        }
      ]
    },
    {
      "pos": "other",
      "words": [
        {
          "words": [
            "accustomed",
            "customary",
            "so",
            "wool"
          ],
          "tran_cn": "其他释义"
        }
      ]
    },
    {
      "pos": "v",
      "words": [
        {
          "words": [
            "authorized"
          ],
          "tran_cn": "确证；使坚定（confirm的过去分词）；批准"
        }
      ]
    }
  ],
  "phrases": [
    {
      "phrase": "confirmed by",
      "tran_cn": "由…确认；由某人确认"
    },
    {
      "phrase": "confirmed cases",
      "tran_cn": "诊断疫情；确认病例"
    },
    {
      "phrase": "confirmed letter of credit",
      "tran_cn": "保兑信用证"
    }
  ],
  "trans": [
    {
      "pos": "adj",
      "tran_cn": "确认的，坚定的，根深蒂固的"
    },
    {
      "pos": "v",
      "tran_cn": "批准(confirm的过去式和过去分词)，证实"
    }
  ],
  "exchange": {}
}