{
  "word": "hustle",
  "ipa": {
    "us": "ˈhʌsl",
    "uk": "ˈhʌsl"
  },
  "sentences": [
    {
      "en": "He could always hustle a buck or two from some sucker.",
      "cn": "他总能从傻瓜身上弄到一两块钱."
    },
    {
      "en": "I don't want to hustle you into a decision.",
      "cn": "我不想催你做决定."
    },
    {
      "en": "I hate all the hustle ( and bustle ) of Saturday shopping.",
      "cn": "我讨厌星期六买东西那 麽 挤来挤去的."
    },
    {
      "en": "If a poet is divorced from the hustle and bustle of life, he can't write inspiring poetry.",
      "cn": "若是离开了沸腾的生活, 诗人是写不出感人的诗篇的."
    },
    {
      "en": "If you're going to be ready in time, you'd better hustle.",
      "cn": "如果你要及时做好准备, 那你最好快点."
    },
    {
      "en": "It seems that he enjoys the hustle and bustle of life in the big city.",
      "cn": "看起来他似乎很喜欢大城市的热闹繁忙的生活。"
    },
    {
      "en": "Jenny was exhausted by the hustle of city life.",
      "cn": "珍妮被城市生活的忙乱弄得筋疲力尽."
    },
    {
      "en": "She waited until they were beyond the hustle of the Washington Saturday night traffic.",
      "cn": "她一直等到他们远离了华盛顿周六晚上的车水马龙。"
    },
    {
      "en": "Some of them hustle souvenirs.",
      "cn": "他们中间一些人强卖土产品."
    },
    {
      "en": "The guards hustled Harry out of the car.",
      "cn": "卫兵们把哈里从车子里拉了出来。"
    },
    {
      "en": "the hustle and bustle of the marketplace",
      "cn": "市场里的熙熙攘攘"
    },
    {
      "en": "The railway station was a scene of hustle and bustle.",
      "cn": "火车站是拥挤喧嚷之所."
    },
    {
      "en": "They recognize that hustle and rush are the allies of superficiality.",
      "cn": "他们认识到匆忙草率就会促成肤浅片面."
    },
    {
      "en": "This place is very quiet, quite different from the hustle and bustle of the cities.",
      "cn": "这个地方很安静, 与城市的拥挤喧嚣十分不同."
    },
    {
      "en": "We can get there in time if we hustle.",
      "cn": "要是我们赶紧些,可以准时到那儿."
    },
    {
      "en": "We need to hustle if we’re going to make this flight.",
      "cn": "要想搭乘这趟班机，我们得抓紧时间。"
    },
    {
      "en": "We're expected to hustle and fight for what we want.",
      "cn": "我们应该为得到自己想要的而不择手段，奋力争取。"
    },
    {
      "en": "You'll have to hustle if you're to get home for supper.",
      "cn": "你想赶回家吃晚饭的话，就得加快速度。"
    }
  ],
  "rel_words": [
    {
      "pos": "n",
      "words": [
        {
          "word": "hustler",
          "tran_cn": " 催促者；妓女；骗子"
        }
      ]
    }
  ],
  "synos": [
    {
      "pos": "n",
      "words": [
        {
          "words": [
            "push",
            "jundy"
          ],
          "tran_cn": "推；奔忙；拥挤喧嚷"
        }
      ]
    },
    {
      "pos": "other",
      "words": [
        {
          "words": [
            "bounce",
            "bump",
            "elbow",
            "haste",
            "hasten",
            "hurry",
            "initiative",
            "jolt",
            "jostle",
            "prod",
            "push",
            "rush",
            "scamper",
            "scramble",
            "scurry",
            "shove",
            "speed",
            "urge"
          ],
          "tran_cn": "其他释义"
        }
      ]
    },
    {
      "pos": "vi",
      "words": [
        {
          "words": [
            "bounce",
            "bump",
            "jolt",
            "jostle",
            "prod",
            "push",
            "shove"
          ],
          "tran_cn": "推;挤"
        }
      ]
    },
    {
      "pos": "vt",
      "words": [
        {
          "words": [
            "hasten",
            "rush",
            "speed",
            "urge"
          ],
          "tran_cn": "催促;促进"
        }
      ]
    }
  ],
  "phrases": [
    {
      "phrase": "hustle and bustle",
      "tran_cn": "熙熙攘攘，忙碌"
    },
    {
      "phrase": "hustle one's butt (或粗俚ass)",
      "tran_cn": "(北美，非正式)麻利点，抓紧点"
    }
  ],
  "trans": [
    {
      "pos": "n",
      "tran_cn": "忙碌，奔忙，挤，推，拥挤喧嚷",
      "tran_en": "busy and noisy activity"
    },
    {
      "pos": "v",
      "tran_cn": "催促，赶紧做；猛推，挤，强迫",
      "tran_en": "to make someone move quickly, especially by pushing them roughly"
    },
    {
      "pos": "vi",
      "tran_cn": "赶紧，硬挤过去，拼命挣钱"
    },
    {
      "pos": "vt& vi.",
      "tran_cn": "催促，硬挤，乱推，硬逼，逼使，强夺"
    }
  ],
  "exchange": {
    "third": [
      "hustles"
    ],
    "past": [
      "hustled"
    ],
    "done": [
      "hustled"
    ],
    "ing": [
      "hustling"
    ]
  }
}